{
	"configurations" : 
	[
		{
			"directories" : 
			[
				{
					"build" : ".",
					"childIndexes" : 
					[
						1
					],
					"jsonFile" : "directory-.-Debug-d0094a50bb2071803777.json",
					"minimumCMakeVersion" : 
					{
						"string" : "3.8"
					},
					"projectIndex" : 0,
					"source" : "."
				},
				{
					"build" : "Lab-02-cross",
					"jsonFile" : "directory-Lab-02-cross-Debug-c61d466f4603c9ca599b.json",
					"minimumCMakeVersion" : 
					{
						"string" : "3.8"
					},
					"parentIndex" : 0,
					"projectIndex" : 0,
					"source" : "Lab-02-cross",
					"targetIndexes" : 
					[
						0
					]
				}
			],
			"name" : "Debug",
			"projects" : 
			[
				{
					"directoryIndexes" : 
					[
						0,
						1
					],
					"name" : "lab2",
					"targetIndexes" : 
					[
						0
					]
				}
			],
			"targets" : 
			[
				{
					"directoryIndex" : 1,
					"id" : "Lab-02-cross::@3101bcbf47e98d69521c",
					"jsonFile" : "target-Lab-02-cross-Debug-45443e61cffa9095a97b.json",
					"name" : "Lab-02-cross",
					"projectIndex" : 0
				}
			]
		}
	],
	"kind" : "codemodel",
	"paths" : 
	{
		"build" : "D:/Study/university/5semester/SP/lab2/lab2/out/build/x64-debug",
		"source" : "D:/Study/university/5semester/SP/lab2/lab2"
	},
	"version" : 
	{
		"major" : 2,
		"minor" : 7
	}
}
